Metadata-Version: 1.0
Name: TracOpenIDDelegate
Version: 1.0
Summary: Add OpenID delegation links to a Trac site.
Home-page: http://trac-hacks.org/wiki/OpenIDDelegatePlugin
Author: Noah Kantrowitz
Author-email: noah@coderanger.net
License: BSD
Keywords: trac plugin
Platform: UNKNOWN
Classifier: Framework :: Trac
Classifier: Development Status :: 1 - Planning
Classifier: Environment :: Web Environment
Classifier: License :: OSI Approved :: BSD License
Classifier: Natural Language :: English
Classifier: Operating System :: OS Independent
Classifier: Programming Language :: Python
